{
    "skill":[
        {
            "skill_ID":1,
            "skill_name":["meetint","会议"]},
        {
            "skill_ID":2,
            "skill_name":["water","取水"]},
        {
            "skill_ID":3,
            "skill_name":["call","呼叫"]}
    ],
    "intent":[
        {
            "intent_ID":1,
            "skill_ID":1,
            "intent_name":["hold_meeting","召开会议"]},
        {
            "intent_ID":2,
            "skill_ID":1,
            "intent_name":["modify_meeting_time","修改会议时间"]},
        {
            "intent_ID":3,
            "skill_ID":1,
            "intent_name":["confirm_meeting","确认会议"]},
        {
            "intent_ID":4,
            "skill_ID":1,
            "intent_name":["cancel_meeting","取消会议"]},
        {
            "intent_ID":5,
            "skill_ID":2,
            "intent_name":["get_water","取水"]},
        {
            "intent_ID":6,
            "skill_ID":2,
            "intent_name":["service_water","水送达"]},
        {
            "intent_ID":7,
            "skill_ID":3,
            "intent_name":["make_call","发起呼叫"]}
    ]
}
